overcast.py
core/__init__.py
core/agent.py
core/client.py
core/config.py
core/correlator.py
core/database.py
core/http_client.py
overcast_sre-0.1.0.dist-info/licenses/LICENSE
overcast_sre-0.1.0.dist-info/METADATA
overcast_sre-0.1.0.dist-info/WHEEL
overcast_sre-0.1.0.dist-info/entry_points.txt
overcast_sre-0.1.0.dist-info/top_level.txt
overcast_sre-0.1.0.dist-info/RECORD
