Metadata-Version: 2.4
Name: overcast-sre
Version: 0.1.0
Summary: AI-powered monitoring and incident management for startups - 3-line integration
Home-page: https://github.com/overcast-ai/overcast-sre
Author: Overcast
Author-email: Overcast <raghavb5120@gmail.com>
License: MIT
Project-URL: Homepage, https://github.com/overcast-ai/overcast-sre
Project-URL: Bug Reports, https://github.com/overcast-ai/overcast-sre/issues
Project-URL: Source, https://github.com/overcast-ai/overcast-sre
Project-URL: Documentation, https://github.com/overcast-ai/overcast-sre#readme
Project-URL: Dashboard, https://overcast.up.railway.app
Keywords: monitoring,observability,incidents,alerting,ai,analytics,dashboard,startup,sre
Classifier: Development Status :: 4 - Beta
Classifier: Intended Audience :: Developers
Classifier: Topic :: System :: Monitoring
Classifier: Topic :: Software Development :: Libraries :: Python Modules
Classifier: License :: OSI Approved :: MIT License
Classifier: Programming Language :: Python :: 3
Classifier: Programming Language :: Python :: 3.8
Classifier: Programming Language :: Python :: 3.9
Classifier: Programming Language :: Python :: 3.10
Classifier: Programming Language :: Python :: 3.11
Classifier: Programming Language :: Python :: 3.12
Classifier: Programming Language :: Python :: 3.13
Requires-Python: >=3.8
License-File: LICENSE
Requires-Dist: flask>=2.0.0
Requires-Dist: rich>=10.0.0
Requires-Dist: requests>=2.25.0
Requires-Dist: openai>=1.0.0
Dynamic: author
Dynamic: home-page
Dynamic: license-file
Dynamic: requires-python
